week1/div3.v
module div3(input clk_in, input rst, output clk_div3);

    logic [1:0] cnt_p;
    logic [1:0] cnt_n;

    always_ff @(posedge clk_in) begin //上升沿 
        if (rst)
            cnt_p <= 2'd0;
        else if (cnt_p != 2'd2)
            cnt_p <= cnt_p + 1'b1;
        else 
            cnt_p <= 0;
    end

    always_ff @(negedge clk_in) begin
        if (rst)
            cnt_n <= 2'd0;
        else if (cnt_n != 2'd2)
            cnt_n <= cnt_n + 1'b1;
        else 
            cnt_n <= 0;
    end

    assign clk_div3 = (cnt_p == 2'd2) | (cnt_n == 2'd2);

endmodule

week1/tb_div3.v
module tb_div3;
    reg clk_in = 0, rst = 1;
    wire clk_div3;

    div3 u(clk_in, rst, clk_div3);
    always #5 clk_in = ~ clk_in;


    initial begin
        $dumpfile("wave.vcd");
        $dumpvars(0, tb_div3);
        #12 rst = 0;
        #200 $finish;
    end
endmodule

week1/wave.vcd
$date
	Sun Jun 07 12:00:53 2026
$end
$version
	Icarus Verilog
$end
$timescale
	1s
$end
$scope module tb_div3 $end
$var wire 1 ! clk_div3 $end
$var reg 1 " clk_in $end
$var reg 1 # rst $end
$scope module u $end
$var wire 1 ! clk_div3 $end
$var wire 1 " clk_in $end
$var wire 1 # rst $end
$var reg 2 $ cnt_n [1:0] $end
$var reg 2 % cnt_p [1:0] $end
$upscope $end
$upscope $end
$enddefinitions $end
$comment Show the parameter values. $end
$dumpall
$end
#0
$dumpvars
bx %
b0 $
1#
0"
x!
$end
#5
0!
b0 %
1"
#10
0"
#12
0#
#15
b1 %
1"
#20
b1 $
0"
#25
1!
b10 %
1"
#30
b10 $
0"
#35
b0 %
1"
#40
0!
b0 $
0"
#45
b1 %
1"
#50
b1 $
0"
#55
1!
b10 %
1"
#60
b10 $
0"
#65
b0 %
1"
#70
0!
b0 $
0"
#75
b1 %
1"
#80
b1 $
0"
#85
1!
b10 %
1"
#90
b10 $
0"
#95
b0 %
1"
#100
0!
b0 $
0"
#105
b1 %
1"
#110
b1 $
0"
#115
1!
b10 %
1"
#120
b10 $
0"
#125
b0 %
1"
#130
0!
b0 $
0"
#135
b1 %
1"
#140
b1 $
0"
#145
1!
b10 %
1"
#150
b10 $
0"
#155
b0 %
1"
#160
0!
b0 $
0"
#165
b1 %
1"
#170
b1 $
0"
#175
1!
b10 %
1"
#180
b10 $
0"
#185
b0 %
1"
#190
0!
b0 $
0"
#195
b1 %
1"
#200
b1 $
0"
#205
1!
b10 %
1"
#210
b10 $
0"
