week2/shift_reg.sv
module shift_reg #(parameter WIDTH=4 //位宽=4
)(
    input  logic             rst,
    input  logic             clk,
    input  logic             en,
    input  logic             serial_in,
    output logic [WIDTH-1:0] q,
    output logic             serial_out
);

    assign serial_out = q[0];

    always_ff @(posedge clk) begin
        if(rst)
            q <= 0;
        else if(en)
            q <= {serial_in, q[WIDTH-1:1]};
    end
endmodule

week2/shift_reg_tb.sv
`timescale 1ns/1ps

module shift_reg_tb;

    logic rst, clk, en;
    logic [3:0] q;
    logic [3:0] expected;
    logic serial_in, serial_out;
    integer errors = 0;

    shift_reg #(.WIDTH(4)) dut(     //例化 给参数WIDTH赋值
        .clk        (clk),
        .rst        (rst),
        .en         (en),
        .q          (q),
        .serial_in  (serial_in),
        .serial_out (serial_out)

    );

    initial clk = 0;  //造时钟
    always #5 clk = ~clk;

    initial begin   //看波形
        $dumpfile("wave.vcd");
        $dumpvars(0,shift_reg_tb);
    end


    task check;    //给激励设置检查任务
        begin
            @(posedge clk);
            #1;
            if(expected !== q) begin
                $display("error t = %t: q = %d, expected = %d",$time, q, expected);
                errors = errors + 1;
            end

            else begin
                $display("PASS t = %t: q = %d",$time, q);
            end
        end
    endtask

    
    initial begin
        rst = 1; en = 0; serial_in = 0;
        expected = 0; check;

        rst = 0; serial_in = 1;
        expected = 0; check;

        en = 1; serial_in = 1;
        expected = 4'b1000; check;

        serial_in = 0;
        expected = 4'b0100; check;

        expected = 4'b0010; check;

        serial_in = 1;
        expected = 4'b1001; check;

        $finish;
    end
endmodule

week2/wave.vcd
$date
	Mon Jun 15 03:16:58 2026
$end
$version
	Icarus Verilog
$end
$timescale
	1ps
$end
$scope module shift_reg_tb $end
$var wire 1 ! serial_out $end
$var wire 4 " q [3:0] $end
$var reg 1 # clk $end
$var reg 1 $ en $end
$var reg 4 % expected [3:0] $end
$var reg 1 & rst $end
$var reg 1 ' serial_in $end
$var integer 32 ( errors [31:0] $end
$scope module dut $end
$var wire 1 # clk $end
$var wire 1 $ en $end
$var wire 1 & rst $end
$var wire 1 ' serial_in $end
$var wire 1 ! serial_out $end
$var parameter 32 ) WIDTH $end
$var reg 4 * q [3:0] $end
$upscope $end
$scope task check $end
$upscope $end
$upscope $end
$enddefinitions $end
$comment Show the parameter values. $end
$dumpall
b100 )
$end
#0
$dumpvars
bx *
b0 (
0'
1&
b0 %
0$
0#
bx "
x!
$end
#5000
0!
b0 "
b0 *
1#
#6000
1'
0&
#10000
0#
#15000
1#
#16000
b1000 %
1$
#20000
0#
#25000
b1000 "
b1000 *
1#
#26000
b100 %
0'
#30000
0#
#35000
b100 "
b100 *
1#
#36000
b10 %
#40000
0#
#45000
b10 "
b10 *
1#
#46000
b1001 %
1'
#50000
0#
#55000
1!
b1001 "
b1001 *
1#
